README.rst
setup.cfg
setup.py
fwf/__init__.py
fwf/parser.py
fwf.egg-info/PKG-INFO
fwf.egg-info/SOURCES.txt
fwf.egg-info/dependency_links.txt
fwf.egg-info/requires.txt
fwf.egg-info/top_level.txt