Metadata-Version: 1.1
Name: fwf
Version: 0.1.0
Summary: Fixed-Width-Field File Format parser and tools
Home-page: https://github.com/nano-labs/pyfwf3
Author: Fabio Pachelli Pacheco
Author-email: nanook@nanook.com.br
License: MIT
Download-URL: https://github.com/nano-labs/pyfwf3/archive/0.1.0.tar.gz
Keywords: file parse parsing EDI X12 fixed-width
Platform: UNKNOWN
Classifier: Development Status :: 4 - Beta
Classifier: Intended Audience :: Developers
Classifier: Intended Audience :: Information Technology
Classifier: Natural Language :: English
Classifier: Topic :: Software Development :: Libraries
Classifier: Topic :: Utilities
Classifier: License :: OSI Approved :: MIT License
Classifier: Programming Language :: Python :: 3
Classifier: Programming Language :: Python :: 3.3
Classifier: Programming Language :: Python :: 3.4
Classifier: Programming Language :: Python :: 3.5
Classifier: Programming Language :: Python :: 3.6
